viz/__init__.py
viz/web_ui.py
viz/htdocs/viz.css
viz/htdocs/viz.js
viz/templates/viz.html
TracVisualization-0.2.dist-info/COPYING
TracVisualization-0.2.dist-info/METADATA
TracVisualization-0.2.dist-info/WHEEL
TracVisualization-0.2.dist-info/entry_points.txt
TracVisualization-0.2.dist-info/top_level.txt
TracVisualization-0.2.dist-info/RECORD
