Metadata-Version: 2.1
Name: TracVisualization
Version: 0.2
Summary: Graphs tables and other data using Google Visualization API
Home-page: https://trac-hacks.org/wiki/VisualizationPlugin
Author: Rob Guttman
Author-email: guttman@alum.mit.edu
License: 3-Clause BSD
Platform: UNKNOWN
Classifier: Framework :: Trac
